LICENSE.md
MANIFEST.in
README.rst
pyproject.toml
requirements.core.txt
setup.py
core_explore_keyword_app/__init__.py
core_explore_keyword_app/admin.py
core_explore_keyword_app/apps.py
core_explore_keyword_app/forms.py
core_explore_keyword_app/menus.py
core_explore_keyword_app/models.py
core_explore_keyword_app/settings.py
core_explore_keyword_app/urls.py
core_explore_keyword_app.egg-info/PKG-INFO
core_explore_keyword_app.egg-info/SOURCES.txt
core_explore_keyword_app.egg-info/dependency_links.txt
core_explore_keyword_app.egg-info/requires.txt
core_explore_keyword_app.egg-info/top_level.txt
core_explore_keyword_app/components/__init__.py
core_explore_keyword_app/components/persistent_query_keyword/__init__.py
core_explore_keyword_app/components/persistent_query_keyword/admin_site.py
core_explore_keyword_app/components/persistent_query_keyword/api.py
core_explore_keyword_app/components/persistent_query_keyword/models.py
core_explore_keyword_app/components/search_operator/__init__.py
core_explore_keyword_app/components/search_operator/admin_site.py
core_explore_keyword_app/components/search_operator/api.py
core_explore_keyword_app/components/search_operator/models.py
core_explore_keyword_app/migrations/0001_initial.py
core_explore_keyword_app/migrations/__init__.py
core_explore_keyword_app/permissions/__init__.py
core_explore_keyword_app/permissions/discover.py
core_explore_keyword_app/permissions/rights.py
core_explore_keyword_app/rest/__init__.py
core_explore_keyword_app/rest/urls.py
core_explore_keyword_app/rest/persistent_query_keyword/__init__.py
core_explore_keyword_app/rest/persistent_query_keyword/serializers.py
core_explore_keyword_app/rest/persistent_query_keyword/views.py
core_explore_keyword_app/rest/search_operators/__init__.py
core_explore_keyword_app/rest/search_operators/serializers.py
core_explore_keyword_app/rest/search_operators/views.py
core_explore_keyword_app/static/core_explore_keyword_app/admin/css/search_ops_manager.css
core_explore_keyword_app/static/core_explore_keyword_app/admin/js/search_operators.raw.js
core_explore_keyword_app/static/core_explore_keyword_app/admin/js/search_ops_manager.js
