Metadata-Version: 2.1
Name: core-explore-keyword-app
Version: 2.19.0
Summary: Exploration by keywords for the curator core project
Home-page: https://github.com/usnistgov/core_explore_keyword_app
Author: NIST IT Lab
Author-email: itl_inquiries@nist.gov
License-File: LICENSE.md
